MagisterPy/__init__.py
MagisterPy/error_handler.py
MagisterPy/jsparser.py
MagisterPy/magister_errors.py
MagisterPy/magister_session.py
MagisterPy/request_manager.py
MagisterPy/response_items.py
magisterpy-0.1.50.dist-info/licenses/LICENSE
magisterpy-0.1.50.dist-info/METADATA
magisterpy-0.1.50.dist-info/WHEEL
magisterpy-0.1.50.dist-info/top_level.txt
magisterpy-0.1.50.dist-info/RECORD
