Metadata-Version: 2.4
Name: MagisterPy
Version: 0.1.50
Summary: A Python package for retrieving information from magister
Home-page: https://github.com/H3LL0U/MagisterPy
Author: H3LL0U
Classifier: Programming Language :: Python :: 3
Classifier: License :: OSI Approved :: MIT License
Classifier: Operating System :: OS Independent
Requires-Python: >=3.9
License-File: LICENSE
Requires-Dist: beautifulsoup4==4.12.3
Requires-Dist: certifi==2024.8.30
Requires-Dist: charset-normalizer==3.4.0
Requires-Dist: idna==3.10
Requires-Dist: requests==2.32.3
Requires-Dist: soupsieve==2.6
Requires-Dist: urllib3==2.2.3
Dynamic: author
Dynamic: classifier
Dynamic: description
Dynamic: description-content-type
Dynamic: home-page
Dynamic: license-file
Dynamic: requires-dist
Dynamic: requires-python
Dynamic: summary
